{
  "0": "ACCOUNTANT",
  "1": "ADVOCATE",
  "2": "AGRICULTURE",
  "3": "APPAREL",
  "4": "ARTS",
  "5": "AUTOMOBILE",
  "6": "AVIATION",
  "7": "BANKING",
  "8": "BPO",
  "9": "BUSINESS-DEVELOPMENT",
  "10": "CHEF",
  "11": "CONSTRUCTION",
  "12": "CONSULTANT",
  "13": "DESIGNER",
  "14": "DIGITAL-MEDIA",
  "15": "ENGINEERING",
  "16": "FINANCE",
  "17": "FITNESS",
  "18": "HEALTHCARE",
  "19": "HR",
  "20": "INFORMATION-TECHNOLOGY",
  "21": "PUBLIC-RELATIONS",
  "22": "SALES",
  "23": "TEACHER"
}